ni_usb_6501/__init__.py
ni_usb_6501/driver.py
ni_usb_6501-0.0.4.dist-info/LICENSE
ni_usb_6501-0.0.4.dist-info/METADATA
ni_usb_6501-0.0.4.dist-info/WHEEL
ni_usb_6501-0.0.4.dist-info/top_level.txt
ni_usb_6501-0.0.4.dist-info/RECORD
