Metadata-Version: 2.2
Name: ni_usb_6501
Version: 0.0.4
Summary: A Python driver for the NI USB 6501 I/O Module
Author-email: Daniel Köpping <daniel.koepping@de.abb.com>
License: MIT
Project-URL: Homepage, https://github.com/dkoep/ni-usb-6501-driver
Project-URL: Repository, https://github.com/dkoep/ni-usb-6501-driver
Project-URL: Issues, https://github.com/dkoep/ni-usb-6501-driver/issues
Keywords: NI USB 6501,National Instruments,Python driver,USB,I/O Module,Industrial automation
Classifier: Programming Language :: Python :: 3
Classifier: Operating System :: OS Independent
Requires-Python: >=3.8
License-File: LICENSE
Requires-Dist: pyusb
